django_ya_model_publisher-0.7.0.dist-info/DESCRIPTION.rst
django_ya_model_publisher-0.7.0.dist-info/METADATA
django_ya_model_publisher-0.7.0.dist-info/RECORD
django_ya_model_publisher-0.7.0.dist-info/WHEEL
django_ya_model_publisher-0.7.0.dist-info/metadata.json
django_ya_model_publisher-0.7.0.dist-info/top_level.txt
publisher/__init__.py
publisher/admin.py
publisher/admin_utils.py
publisher/app_settings.py
publisher/constants.py
publisher/forms.py
publisher/managers.py
publisher/models.py
publisher/permissions.py
publisher/signal_handlers.py
publisher/signals.py
publisher/utils.py
publisher/version.py
publisher/views.py
publisher/management/__init__.py
publisher/management/commands/__init__.py
publisher/management/commands/publish_model.py
publisher/migrations/0001_initial.py
publisher/migrations/0002_auto_20171122_1551.py
publisher/migrations/0003_auto_20171222_0706.py
publisher/migrations/0004_auto_20180102_0502.py
publisher/migrations/__init__.py
publisher/static/publisher/publisher.css
publisher/static/publisher/publisher.js
publisher/static/publisher/images/icons.png
publisher/templates/publisher/change_form.html
publisher/templates/publisher/change_list_publish.html
publisher/templates/publisher/change_list_publish_status.html
publisher/templates/publisher/publish_history.html
publisher/templates/publisher/publisher_requests.html
publisher/templates/publisher/hvad/change_form.html
publisher/templates/publisher/includes/current_state_info.html
publisher/templates/publisher/includes/object_tools_buttons.html
publisher/templates/publisher/includes/state_history.html
publisher/templates/publisher/includes/submit_buttons_bottom.html
publisher/templates/publisher/includes/submit_row.html
publisher/templates/publisher/parler/change_form.html
publisher_cms/__init__.py
publisher_cms/cms_toolbars.py
publisher_cms/views.py
publisher_cms/templates/admin/publisher_cms/change_form.html
publisher_cms/templates/admin/publisher_cms/reply_publish.html
publisher_cms/templates/admin/publisher_cms/request_publish.html
publisher_test_project/__init__.py
publisher_test_project/constants.py
publisher_test_project/fixtures.py
publisher_test_project/manage.py
publisher_test_project/settings.py
publisher_test_project/urls.py
