Metadata-Version: 2.0
Name: django-ya-model-publisher
Version: 0.7.0
Summary: Publisher workflow for django models and Django CMS pages.
Home-page: https://github.com/wearehoods/django-ya-model-publisher
Author: Jens Diemer
Author-email: model-ya-publisher@jensdiemer.de
License: BSD
Keywords: publisher django cms parler workflow model-publisher
Platform: UNKNOWN
Classifier: Development Status :: 4 - Beta
Classifier: Environment :: Web Environment
Classifier: Framework :: Django
Classifier: Intended Audience :: Developers
Classifier: License :: OSI Approved :: BSD License
Classifier: Operating System :: OS Independent
Classifier: Programming Language :: Python
Classifier: Programming Language :: Python :: 3
Classifier: Programming Language :: Python :: 3.5
Classifier: Programming Language :: Python :: 3.6
Classifier: Topic :: Internet :: WWW/HTTP :: Dynamic Content :: Content Management System
Classifier: Topic :: Software Development :: Libraries :: Python Modules
Requires-Python: >=3.5
